speech_recognition/__init__.py
speech_recognition/__main__.py
speech_recognition/flac-linux-x86
speech_recognition/flac-linux-x86_64
speech_recognition/flac-mac
speech_recognition/flac-win32.exe
speech_recognition/pocketsphinx-data/en-US/LICENSE.txt
speech_recognition/pocketsphinx-data/en-US/language-model.lm.bin
speech_recognition/pocketsphinx-data/en-US/pronounciation-dictionary.dict
speech_recognition/pocketsphinx-data/en-US/acoustic-model/README
speech_recognition/pocketsphinx-data/en-US/acoustic-model/feat.params
speech_recognition/pocketsphinx-data/en-US/acoustic-model/mdef
speech_recognition/pocketsphinx-data/en-US/acoustic-model/means
speech_recognition/pocketsphinx-data/en-US/acoustic-model/noisedict
speech_recognition/pocketsphinx-data/en-US/acoustic-model/sendump
speech_recognition/pocketsphinx-data/en-US/acoustic-model/transition_matrices
speech_recognition/pocketsphinx-data/en-US/acoustic-model/variances
SpeechRecognition_ForkedVersion-3.9.2.dist-info/LICENSE-FLAC.txt
SpeechRecognition_ForkedVersion-3.9.2.dist-info/LICENSE.txt
SpeechRecognition_ForkedVersion-3.9.2.dist-info/METADATA
SpeechRecognition_ForkedVersion-3.9.2.dist-info/WHEEL
SpeechRecognition_ForkedVersion-3.9.2.dist-info/top_level.txt
SpeechRecognition_ForkedVersion-3.9.2.dist-info/RECORD
