Metadata-Version: 2.1
Name: SpeechRecognition_ForkedVersion
Version: 3.9.2
Summary: Forked version of orignal project with now capability to use speaker as a source for listening
Home-page: https://github.com/Hashah2311/speech_recognition_fork
Author: Hashah2311
Author-email: shahharshit063@gmail.com
License: BSD
Keywords: speech recognition voice sphinx google wit bing api houndify ibm snowboy speaker
Classifier: Development Status :: 5 - Production/Stable
Classifier: Intended Audience :: Developers
Classifier: Natural Language :: English
Classifier: License :: OSI Approved :: BSD License
Classifier: Operating System :: Microsoft :: Windows
Classifier: Operating System :: POSIX :: Linux
Classifier: Operating System :: MacOS :: MacOS X
Classifier: Operating System :: Other OS
Classifier: Programming Language :: Python
Classifier: Programming Language :: Python :: 2
Classifier: Programming Language :: Python :: 2.7
Classifier: Programming Language :: Python :: 3
Classifier: Programming Language :: Python :: 3.3
Classifier: Programming Language :: Python :: 3.4
Classifier: Programming Language :: Python :: 3.5
Classifier: Programming Language :: Python :: 3.6
Classifier: Topic :: Software Development :: Libraries :: Python Modules
Classifier: Topic :: Multimedia :: Sound/Audio :: Speech
License-File: LICENSE-FLAC.txt
License-File: LICENSE.txt
